Metadata-Version: 2.3
Name: caqtus-devices-orca-quest
Version: 2.4.1
Summary: Contains the caqtus device extension for the Hamamatsu Orca Quest camera.
Author-email: light-scattering-io <lecaqtus66@gmail.com>
License: Copyright 2024 Université Paris-Saclay
License-File: license.md
Requires-Python: >=3.12
Requires-Dist: caqtus-suite>=6.14.0
